text_blind_watermark/__init__.py
text_blind_watermark/text_blind_watermark.py
text_blind_watermark/text_blind_watermark2.py
text_blind_watermark-0.4.2.dist-info/LICENSE
text_blind_watermark-0.4.2.dist-info/METADATA
text_blind_watermark-0.4.2.dist-info/WHEEL
text_blind_watermark-0.4.2.dist-info/top_level.txt
text_blind_watermark-0.4.2.dist-info/RECORD
