Metadata-Version: 2.1
Name: text_blind_watermark
Version: 0.4.2
Summary: Text Blind Watermark in Python
Home-page: https://github.com/guofei9987/text_blind_watermark
Author: Guo Fei
Author-email: guofei9987@foxmail.com
License: MIT
Platform: linux
Platform: windows
Platform: macos
Requires-Python: >=3.5
License-File: LICENSE
Requires-Dist: crypt_tool>=0.1.3
